Metadata-Version: 2.1
Name: simimgs
Version: 0.0.15
Summary: A tool for compare image similarities using SSIM
Home-page: https://github.com/liyefei737/simimgs
Author: Yefei Li
Author-email: abc@gmail.com
License: UNKNOWN
Platform: UNKNOWN
Classifier: Programming Language :: Python :: 3
Classifier: License :: OSI Approved :: MIT License
Classifier: Operating System :: OS Independent
Requires-Python: >=3.6
